sphinx_pyproject/__init__.py
sphinx_pyproject/py.typed
sphinx_pyproject-0.2.0.dist-info/LICENSE
sphinx_pyproject-0.2.0.dist-info/METADATA
sphinx_pyproject-0.2.0.dist-info/WHEEL
sphinx_pyproject-0.2.0.dist-info/entry_points.txt
sphinx_pyproject-0.2.0.dist-info/RECORD
