Metadata-Version: 2.1
Name: sphinx-pyproject
Version: 0.2.0
Summary: Move some of your Sphinx configuration into pyproject.toml
Author-email: Dominic Davis-Foster <dominic@davis-foster.co.uk>
License: MIT
Keywords: documentation,pep621,sphinx,toml
Home-page: https://github.com/sphinx-toolbox/sphinx-pyproject
Project-URL: Issue Tracker, https://github.com/sphinx-toolbox/sphinx-pyproject/issues
Project-URL: Source Code, https://github.com/sphinx-toolbox/sphinx-pyproject
Project-URL: Documentation, https://sphinx-pyproject.readthedocs.io/en/latest
Platform: Windows
Platform: macOS
Platform: Linux
Classifier: Development Status :: 4 - Beta
Classifier: Framework :: Sphinx
Classifier: Intended Audience :: Developers
Classifier: License :: OSI Approved :: MIT License
Classifier: Operating System :: OS Independent
Classifier: Programming Language :: Python
Classifier: Programming Language :: Python :: 3 :: Only
Classifier: Programming Language :: Python :: 3.6
Classifier: Programming Language :: Python :: 3.7
Classifier: Programming Language :: Python :: 3.8
Classifier: Programming Language :: Python :: 3.9
Classifier: Programming Language :: Python :: 3.10
Classifier: Programming Language :: Python :: 3.11
Classifier: Programming Language :: Python :: Implementation :: CPython
Classifier: Programming Language :: Python :: Implementation :: PyPy
Classifier: Topic :: Documentation
Classifier: Topic :: Documentation :: Sphinx
Classifier: Topic :: Software Development :: Documentation
Classifier: Topic :: Utilities
Classifier: Typing :: Typed
Requires-Python: >=3.6
Requires-Dist: dom-toml>=0.3.0
Requires-Dist: domdf-python-tools>=2.7.0
